<DOMSymbolItem xmlns="http://ns.adobe.com/xfl/2008/" xmlns:xsi="http://www.w3.org/2001/XMLSchema-instance" name="Symbol 1041" lastModified="1648300950" symbolType="graphic">
     <timeline>
          <DOMTimeline name="Symbol 1041" currentFrame="0">
               <layers>
                    <DOMLayer name="Layer 1">
                         <frames>
                              <DOMFrame index="0" motionTweenScale="false" keyMode="8192">
                                   <elements>
                                        <DOMShape isFloating="true">
                                             <fills>
                                                  <FillStyle index="1">
                                                       <BitmapFill bitmapPath="bitmap305.png">
                                                            <matrix>
                                                                 <Matrix tx="113.4" ty="-30.0" a="-9.8614501953125" d="9.8614501953125" b="-1.47674560546875" c="-1.47674560546875"/>
                                                            </matrix>
                                                       </BitmapFill>
                                                  </FillStyle>
                                                  <FillStyle index="2">
                                                       <BitmapFill bitmapPath="bitmap305.png">
                                                            <matrix>
                                                                 <Matrix tx="113.4" ty="-27.5" a="-9.8614501953125" d="9.8614501953125" b="-1.47674560546875" c="-1.47674560546875"/>
                                                            </matrix>
                                                       </BitmapFill>
                                                  </FillStyle>
                                             </fills>
                                             <strokes/>
                                             <edges>
                                                  <Edge fillStyle0="0" fillStyle1="1" strokeStyle="0" edges="! 1207 -21[ 1254 -47 1321 -75[ 1506 -153 1595 -167[ 1547 -143 1331 -11| 1192 74| 1197 92[ 1201 110 1201 183| 1212 205[ 1251 291 1251 396[ 1251 543 1232 628[ 1207 737 1137 827[ 992 1015 500 1271| 495 1266[ 959 994 1092 822[ 1160 734 1185 630[ 1206 545 1206 403[ 1206 355 1180 295| 1114 460[ 1032 647 991 691[ 877 815 631 966[ 364 1130 240 1130[ 210 1130 195 1115[ 619 981 902 683[ 1129 446 1153 243[ 1110 168 1031 76| 1080 82[ 1075 74 1075 60[ 1075 7 1177 -73| 1321 -182[ 1288 -145 1215 -33| 1207 -21"/>
                                                  <Edge fillStyle0="0" fillStyle1="1" strokeStyle="0" edges="! 1139 107| 1137 108| 1140 110| 1139 107"/>
                                                  <Edge fillStyle0="0" fillStyle1="2" strokeStyle="0" edges="! 563 91[ 580 87 500 158[ 501 171 468 186| 359 278[ 126 470 -77 600[ -82 612 -82 587[ -82 549 179 324[ 236 275 286 235[ -48 302 -280 391| -285 386[ -213 306 108 179[ 411 59 540 45| 557 49[ 565 52 565 67[ 565 83 556 89| 540 95| 563 91"/>
                                             </edges>
                                        </DOMShape>
                                   </elements>
                              </DOMFrame>
                         </frames>
                    </DOMLayer>
                    <DOMLayer name="Layer 2">
                         <frames>
                              <DOMFrame index="0" motionTweenScale="false" keyMode="8192">
                                   <elements>
                                        <DOMShape isFloating="true">
                                             <fills>
                                                  <FillStyle index="1">
                                                       <BitmapFill bitmapPath="bitmap305.png">
                                                            <matrix>
                                                                 <Matrix tx="113.4" ty="-30.0" a="-9.8614501953125" d="9.8614501953125" b="-1.47674560546875" c="-1.47674560546875"/>
                                                            </matrix>
                                                       </BitmapFill>
                                                  </FillStyle>
                                             </fills>
                                             <strokes/>
                                             <edges>
                                                  <Edge fillStyle0="1" fillStyle1="0" strokeStyle="0" edges="! 1137 179[ 1191 7 1100 12[ 1010 16 798 4[ 585 -11 525 29[ 465 68 256 369[ 48 668 18 976[ -12 1283 8 1362[ 178 1268 250 1172| 268 1269[ 330 1230 486 1102| 636 950[ 657 929 601 981[ 931 652 1008 502[ 1084 351 1137 179"/>
                                             </edges>
                                        </DOMShape>
                                   </elements>
                              </DOMFrame>
                         </frames>
                    </DOMLayer>
               </layers>
          </DOMTimeline>
     </timeline>
</DOMSymbolItem>
