<DOMSymbolItem xmlns="http://ns.adobe.com/xfl/2008/" xmlns:xsi="http://www.w3.org/2001/XMLSchema-instance" name="Symbol 8611" lastModified="1648300950">
     <timeline>
          <DOMTimeline name="Symbol 8611">
               <layers>
                    <DOMLayer name="Layer 1" color="#e329a6" current="true" isSelected="true">
                         <frames>
                              <DOMFrame index="0" keyMode="9728">
                                   <elements>
                                        <DOMShape isFloating="true">
                                             <fills>
                                                  <FillStyle index="1">
                                                       <SolidColor color="#000000"/>
                                                  </FillStyle>
                                             </fills>
                                             <strokes/>
                                             <edges>
                                                  <Edge fillStyle0="0" fillStyle1="1" strokeStyle="0" edges="! 3289 2700[ 3113 2993 2634 2993[ 2013 2993 1811 2763[ 1741 2682 1722 2572[ 1714 2527 1714 2416| 1716 2233[ 1720 2170 1747 2004[ 1764 1827 1764 1596| 1754 1543[ 1754 1504 1763 1475| 1761 1230[ 1760 1079 1727 982[ 1693 885 1679 868[ 1665 850 1665 844| 1665 843[ 1604 736 1735 725[ 1865 713 1924 944[ 1982 1174 1975 1529[ 2295 1312 2344 1088[ 2280 1043 2259 1001[ 2244 972 2244 923[ 2244 868 2284 836[ 2323 804 2468 883| 2714 1021[ 2714 1175 2640 1239[ 2569 1350 2415 1469[ 2202 1626 1974 1745[ 1940 2023 1936 2194[ 1931 2364 1964 2450[ 1997 2536 2068 2580[ 2138 2623 2432 2612[ 2725 2600 2891 2530[ 3057 2459 3125 2301[ 3189 2151 3204 1978[ 3330 2041 3362 2183[ 3381 2269 3364 2380[ 3374 2559 3289 2700"/>
                                                  <Edge fillStyle0="0" fillStyle1="1" strokeStyle="0" edges="! 2538 201[ 2486 337 2364 342[ 2242 346 2033 379[ 1758 466 1604 506| 1534 523[ 1493 507 1446 691[ 1399 875 1347 993[ 1468 870 1519 868[ 1569 865 1535 1099[ 1500 1333 1132 2033| 863 2482[ 744 2669 615 2781[ 486 2892 390 2938[ 293 2983 132 2998[ -29 3013 64 2937[ 157 2860 232 2812[ 521 2561 585 2513[ 667 2451 838 2158| 895 2061[ 822 2038 744 1993[ 594 1907 581 1814[ 567 1720 693 1753| 1027 1833| 1214 1346[ 1303 1122 1097 1241| 1094 1236[ 912 1320 703 1481[ 494 1642 414 1668[ 333 1693 294 1620[ 275 1582 274 1540[ 274 1462 365 1398[ 513 1310 624 1231[ 690 1185 799 1077[ 920 957 962 923[ 1212 725 1207 616| 1206 580[ 986 711 579 713[ 136 633 36 565[ 3 543 0 512[ -1 495 4 472[ 4 376 25 391[ 46 405 358 466[ 669 527 1085 384[ 1501 240 1821 122[ 2141 3 2244 0[ 2347 -3 2469 30[ 2590 63 2538 201"/>
                                             </edges>
                                        </DOMShape>
                                   </elements>
                              </DOMFrame>
                         </frames>
                    </DOMLayer>
               </layers>
          </DOMTimeline>
     </timeline>
</DOMSymbolItem>
