<DOMSymbolItem xmlns="http://ns.adobe.com/xfl/2008/" xmlns:xsi="http://www.w3.org/2001/XMLSchema-instance" name="Symbol 3715" lastModified="1648300950">
     <timeline>
          <DOMTimeline name="Symbol 3715">
               <layers>
                    <DOMLayer name="Layer 1" color="#d39fcc" current="true" isSelected="true">
                         <frames>
                              <DOMFrame index="0" keyMode="9728">
                                   <elements>
                                        <DOMShape isFloating="true">
                                             <fills>
                                                  <FillStyle index="1">
                                                       <SolidColor color="#ffcc00" alpha="1.0"/>
                                                  </FillStyle>
                                                  <FillStyle index="2">
                                                       <SolidColor color="#feeba3" alpha="1.0"/>
                                                  </FillStyle>
                                                  <FillStyle index="3">
                                                       <SolidColor color="#c19a02" alpha="1.0"/>
                                                  </FillStyle>
                                                  <FillStyle index="4">
                                                       <SolidColor color="#7e6501" alpha="1.0"/>
                                                  </FillStyle>
                                                  <FillStyle index="5">
                                                       <SolidColor color="#ffffff" alpha="1.0"/>
                                                  </FillStyle>
                                             </fills>
                                             <strokes>
                                                  <StrokeStyle index="1">
                                                       <SolidStroke weight="1.0" scaleMode="normal">
                                                            <fill>
                                                                 <SolidColor color="#000000"/>
                                                            </fill>
                                                       </SolidStroke>
                                                  </StrokeStyle>
                                                  <StrokeStyle index="2">
                                                       <SolidStroke weight="0.05" solidStyle="hairline" scaleMode="normal">
                                                            <fill>
                                                                 <SolidColor color="#000000"/>
                                                            </fill>
                                                       </SolidStroke>
                                                  </StrokeStyle>
                                             </strokes>
                                             <edges>
                                                  <Edge fillStyle0="3" fillStyle1="1" strokeStyle="0" edges="! 767 469| 825 414| 867 409| 843 465"/>
                                                  <Edge fillStyle0="3" fillStyle1="2" strokeStyle="0" edges="! 843 465| 864 454"/>
                                                  <Edge fillStyle0="3" fillStyle1="0" strokeStyle="1" edges="! 864 454| 972 352"/>
                                                  <Edge fillStyle0="3" fillStyle1="1" strokeStyle="0" edges="! 972 352| 957 356"/>
                                                  <Edge fillStyle0="3" fillStyle1="2" strokeStyle="0" edges="! 957 356| 745 416"/>
                                                  <Edge fillStyle0="3" fillStyle1="4" strokeStyle="0" edges="! 745 416| 634 484[ 588 514 559 526"/>
                                                  <Edge fillStyle0="3" fillStyle1="5" strokeStyle="0" edges="! 559 526| 574 531"/>
                                                  <Edge fillStyle0="3" fillStyle1="1" strokeStyle="0" edges="! 574 531| 762 449| 762 450| 737 498"/>
                                                  <Edge fillStyle0="3" fillStyle1="2" strokeStyle="0" edges="! 737 498| 767 469"/>
                                                  <Edge fillStyle0="1" fillStyle1="2" strokeStyle="0" edges="! 767 469| 747 505| 747 506[ 783 496 843 465"/>
                                                  <Edge fillStyle0="0" fillStyle1="2" strokeStyle="1" edges="! 866 339| 962 351"/>
                                                  <Edge fillStyle0="0" fillStyle1="1" strokeStyle="1" edges="! 962 351| 972 352"/>
                                                  <Edge fillStyle0="1" fillStyle1="2" strokeStyle="0" edges="! 962 351| 957 356"/>
                                                  <Edge fillStyle0="3" fillStyle1="1" strokeStyle="0" edges="! 486 19| 486 0"/>
                                                  <Edge fillStyle0="3" fillStyle1="0" strokeStyle="1" edges="! 486 0| 458 59"/>
                                                  <Edge fillStyle0="3" fillStyle1="1" strokeStyle="0" edges="! 458 59| 465 121| 464 171"/>
                                                  <Edge fillStyle0="3" fillStyle1="4" strokeStyle="0" edges="! 464 171| 485 127| 487 131"/>
                                                  <Edge fillStyle0="3" fillStyle1="2" strokeStyle="0" edges="! 487 131| 486 19"/>
                                                  <Edge fillStyle0="1" fillStyle1="2" strokeStyle="0" edges="! 486 19[ 489 16 493 15"/>
                                                  <Edge fillStyle0="1" fillStyle1="0" strokeStyle="1" edges="! 493 15| 486 0"/>
                                                  <Edge fillStyle0="2" fillStyle1="4" strokeStyle="0" edges="! 487 131| 487 139"/>
                                                  <Edge fillStyle0="2" fillStyle1="5" strokeStyle="0" edges="! 487 139| 490 178| 495 277[ 495 331 502 379[ 507 416 517 435| 523 452| 522 454| 556 454| 661 443"/>
                                                  <Edge fillStyle0="2" fillStyle1="4" strokeStyle="0" edges="! 661 443| 745 416"/>
                                                  <Edge fillStyle0="1" fillStyle1="3" strokeStyle="0" edges="! 415 150| 423 172| 427 184"/>
                                                  <Edge fillStyle0="1" fillStyle1="4" strokeStyle="0" edges="! 427 184| 440 222| 464 171"/>
                                                  <Edge fillStyle0="4" fillStyle1="5" strokeStyle="0" edges="! 487 226| 487 139"/>
                                                  <Edge fillStyle0="4" fillStyle1="3" strokeStyle="0" edges="! 427 184| 407 219[ 407 238 362 278| 349 292"/>
                                                  <Edge fillStyle0="4" fillStyle1="4" strokeStyle="1" edges="! 349 292| 344 301"/>
                                                  <Edge fillStyle0="4" fillStyle1="0" strokeStyle="1" edges="! 344 301| 339 310"/>
                                                  <Edge fillStyle0="4" fillStyle1="2" strokeStyle="0" edges="! 339 310| 354 329"/>
                                                  <Edge fillStyle0="4" fillStyle1="3" strokeStyle="0" edges="! 354 329| 374 313| 413 279| 423 269| 487 226"/>
                                                  <Edge fillStyle0="5" fillStyle1="3" strokeStyle="0" edges="! 487 226| 487 492"/>
                                                  <Edge fillStyle0="5" fillStyle1="2" strokeStyle="0" edges="! 487 492| 490 495"/>
                                                  <Edge fillStyle0="5" fillStyle1="1" strokeStyle="0" edges="! 490 495| 564 474"/>
                                                  <Edge fillStyle0="5" fillStyle1="4" strokeStyle="0" edges="! 564 474| 662 443| 661 443"/>
                                                  <Edge fillStyle0="1" fillStyle1="2" strokeStyle="0" edges="! 555 147[ 522 173 522 194| 524 211| 594 359| 632 310"/>
                                                  <Edge fillStyle0="1" fillStyle1="0" strokeStyle="1" edges="! 632 310| 555 147"/>
                                                  <Edge fillStyle0="2" fillStyle1="0" strokeStyle="1" edges="! 555 147| 493 15"/>
                                                  <Edge fillStyle0="1" fillStyle1="0" strokeStyle="1" edges="! 458 59| 415 150"/>
                                                  <Edge fillStyle0="3" fillStyle1="0" strokeStyle="1" edges="! 415 150| 349 292"/>
                                                  <Edge fillStyle0="4" fillStyle1="0" strokeStyle="0" edges="! 349 292| 348 292| 344 301"/>
                                                  <Edge fillStyle0="1" fillStyle1="2" strokeStyle="0" edges="! 550 303| 521 412| 521 413| 552 383| 572 359[ 572 347 550 303"/>
                                                  <Edge fillStyle0="1" fillStyle1="3" strokeStyle="0" edges="! 466 273| 425 306| 391 339[ 391 350 421 375| 465 409| 472 346| 467 274| 466 273"/>
                                                  <Edge fillStyle0="1" fillStyle1="3" strokeStyle="0" edges="! 464 468| 465 464| 447 446| 440 438"/>
                                                  <Edge fillStyle0="1" fillStyle1="2" strokeStyle="0" edges="! 440 438| 464 468"/>
                                                  <Edge fillStyle0="3" fillStyle1="2" strokeStyle="0" edges="! 464 468| 477 486"/>
                                                  <Edge fillStyle0="3" fillStyle1="5" strokeStyle="0" edges="! 477 486| 478 486| 487 498"/>
                                                  <Edge fillStyle0="3" fillStyle1="2" strokeStyle="0" edges="! 487 498| 487 492"/>
                                                  <Edge fillStyle0="5" fillStyle1="2" strokeStyle="0" edges="! 477 486| 452 477| 329 430| 309 421"/>
                                                  <Edge fillStyle0="5" fillStyle1="1" strokeStyle="0" edges="! 309 421| 275 407"/>
                                                  <Edge fillStyle0="5" fillStyle1="2" strokeStyle="0" edges="! 275 407| 277 406| 206 375"/>
                                                  <Edge fillStyle0="5" fillStyle1="1" strokeStyle="0" edges="! 206 375| 201 375| 198 374| 168 361| 157 355"/>
                                                  <Edge fillStyle0="5" fillStyle1="2" strokeStyle="0" edges="! 157 355| 108 339"/>
                                                  <Edge fillStyle0="5" fillStyle1="0" strokeStyle="0" edges="! 108 339| 107 339"/>
                                                  <Edge fillStyle0="5" fillStyle1="0" strokeStyle="1" edges="! 107 339| 19 350"/>
                                                  <Edge fillStyle0="5" fillStyle1="2" strokeStyle="0" edges="! 19 350| 25 359"/>
                                                  <Edge fillStyle0="5" fillStyle1="3" strokeStyle="2" edges="! 25 359| 27 359"/>
                                                  <Edge fillStyle0="5" fillStyle1="4" strokeStyle="0" edges="! 27 359| 132 386"/>
                                                  <Edge fillStyle0="5" fillStyle1="0" strokeStyle="0" edges="! 132 386| 124 382"/>
                                                  <Edge fillStyle0="5" fillStyle1="1" strokeStyle="0" edges="! 124 382| 151 380[ 141 383 139 387"/>
                                                  <Edge fillStyle0="5" fillStyle1="4" strokeStyle="0" edges="! 139 387| 253 423"/>
                                                  <Edge fillStyle0="5" fillStyle1="3" strokeStyle="0" edges="! 253 423| 425 478"/>
                                                  <Edge fillStyle0="5" fillStyle1="4" strokeStyle="0" edges="! 425 478| 487 498"/>
                                                  <Edge fillStyle0="2" fillStyle1="1" strokeStyle="0" edges="! 487 498| 490 495"/>
                                                  <Edge fillStyle0="0" fillStyle1="1" strokeStyle="1" edges="! 709 320| 737 323"/>
                                                  <Edge fillStyle0="0" fillStyle1="2" strokeStyle="1" edges="! 737 323| 794 330"/>
                                                  <Edge fillStyle0="0" fillStyle1="1" strokeStyle="1" edges="! 794 330| 866 339"/>
                                                  <Edge fillStyle0="2" fillStyle1="1" strokeStyle="0" edges="! 866 339| 802 358| 738 377| 765 380| 753 379| 690 407| 566 436| 617 382[ 632 371 660 367| 719 375| 741 364[ 780 345 794 330"/>
                                                  <Edge fillStyle0="1" fillStyle1="2" strokeStyle="0" edges="! 709 320| 687 325[ 642 336 630 355| 628 363| 648 366| 737 323"/>
                                                  <Edge fillStyle0="0" fillStyle1="2" strokeStyle="1" edges="! 632 310| 709 320"/>
                                                  <Edge fillStyle0="2" fillStyle1="1" strokeStyle="0" edges="! 157 355| 152 352| 158 350[ 193 345 260 322| 281 319"/>
                                                  <Edge fillStyle0="2" fillStyle1="3" strokeStyle="0" edges="! 281 319[ 323 316 347 342| 294 363| 284 366| 279 368| 262 369"/>
                                                  <Edge fillStyle0="2" fillStyle1="1" strokeStyle="0" edges="! 262 369| 206 375"/>
                                                  <Edge fillStyle0="2" fillStyle1="0" strokeStyle="1" edges="! 19 350| 0 352"/>
                                                  <Edge fillStyle0="2" fillStyle1="3" strokeStyle="2" edges="! 0 352| 25 359"/>
                                                  <Edge fillStyle0="0" fillStyle1="3" strokeStyle="1" edges="! 13 364| 0 352"/>
                                                  <Edge fillStyle0="0" fillStyle1="4" strokeStyle="0" edges="! 19 370| 13 364"/>
                                                  <Edge fillStyle0="3" fillStyle1="4" strokeStyle="0" edges="! 13 364| 27 359"/>
                                                  <Edge fillStyle0="0" fillStyle1="3" strokeStyle="1" edges="! 96 443| 88 435"/>
                                                  <Edge fillStyle0="0" fillStyle1="4" strokeStyle="1" edges="! 88 435| 19 370"/>
                                                  <Edge fillStyle0="0" fillStyle1="4" strokeStyle="0" edges="! 132 386| 133 385"/>
                                                  <Edge fillStyle0="0" fillStyle1="1" strokeStyle="2" edges="! 133 385| 124 382"/>
                                                  <Edge fillStyle0="1" fillStyle1="4" strokeStyle="2" edges="! 133 385| 139 387"/>
                                                  <Edge fillStyle0="3" fillStyle1="4" strokeStyle="0" edges="! 253 423| 211 429| 181 437| 164 419| 146 422| 88 435"/>
                                                  <Edge fillStyle0="3" fillStyle1="1" strokeStyle="0" edges="! 96 443| 201 457| 283 542| 274 533| 234 537| 188 529"/>
                                                  <Edge fillStyle0="3" fillStyle1="0" strokeStyle="1" edges="! 188 529| 250 588| 248 599"/>
                                                  <Edge fillStyle0="3" fillStyle1="2" strokeStyle="0" edges="! 248 599| 307 574"/>
                                                  <Edge fillStyle0="3" fillStyle1="4" strokeStyle="0" edges="! 307 574| 308 568| 304 564| 425 478"/>
                                                  <Edge fillStyle0="1" fillStyle1="3" strokeStyle="0" edges="! 376 356| 378 352| 373 352"/>
                                                  <Edge fillStyle0="1" fillStyle1="2" strokeStyle="0" edges="! 373 352| 376 356"/>
                                                  <Edge fillStyle0="3" fillStyle1="2" strokeStyle="0" edges="! 376 356| 440 438"/>
                                                  <Edge fillStyle0="2" fillStyle1="3" strokeStyle="0" edges="! 373 352| 354 329"/>
                                                  <Edge fillStyle0="3" fillStyle1="1" strokeStyle="0" edges="! 281 319| 280 321[ 266 350 262 369"/>
                                                  <Edge fillStyle0="2" fillStyle1="1" strokeStyle="0" edges="! 275 407| 280 405| 336 393| 385 396| 411 450| 309 421"/>
                                                  <Edge fillStyle0="1" fillStyle1="3" strokeStyle="0" edges="! 246 464| 288 542| 334 520| 380 494| 246 464"/>
                                                  <Edge fillStyle0="0" fillStyle1="2" strokeStyle="1" edges="! 108 339| 339 310"/>
                                                  <Edge fillStyle0="2" fillStyle1="3" strokeStyle="0" edges="! 315 607| 314 607| 333 595| 375 570"/>
                                                  <Edge fillStyle0="2" fillStyle1="4" strokeStyle="0" edges="! 375 570| 440 531| 481 507| 455 544"/>
                                                  <Edge fillStyle0="2" fillStyle1="3" strokeStyle="0" edges="! 455 544| 363 673"/>
                                                  <Edge fillStyle0="2" fillStyle1="5" strokeStyle="0" edges="! 363 673| 335 743| 313 792| 295 802| 285 817[ 280 823 280 832| 279 847| 255 877| 248 891| 197 919"/>
                                                  <Edge fillStyle0="2" fillStyle1="0" strokeStyle="0" edges="! 197 919| 200 918"/>
                                                  <Edge fillStyle0="2" fillStyle1="0" strokeStyle="1" edges="! 200 918| 284 871"/>
                                                  <Edge fillStyle0="2" fillStyle1="1" strokeStyle="0" edges="! 284 871| 289 864"/>
                                                  <Edge fillStyle0="2" fillStyle1="3" strokeStyle="0" edges="! 289 864| 320 811| 361 765| 447 717| 446 718"/>
                                                  <Edge fillStyle0="2" fillStyle1="1" strokeStyle="0" edges="! 446 718| 464 708[ 451 755 388 814"/>
                                                  <Edge fillStyle0="2" fillStyle1="0" strokeStyle="1" edges="! 388 814| 486 759| 494 764"/>
                                                  <Edge fillStyle0="2" fillStyle1="4" strokeStyle="0" edges="! 494 764| 493 700"/>
                                                  <Edge fillStyle0="2" fillStyle1="3" strokeStyle="0" edges="! 493 700| 492 668"/>
                                                  <Edge fillStyle0="2" fillStyle1="4" strokeStyle="0" edges="! 492 668| 492 667"/>
                                                  <Edge fillStyle0="2" fillStyle1="1" strokeStyle="0" edges="! 492 667| 491 655| 490 652| 491 646"/>
                                                  <Edge fillStyle0="2" fillStyle1="4" strokeStyle="0" edges="! 491 646| 488 522"/>
                                                  <Edge fillStyle0="2" fillStyle1="1" strokeStyle="0" edges="! 488 522| 487 499"/>
                                                  <Edge fillStyle0="2" fillStyle1="3" strokeStyle="0" edges="! 487 499| 475 503"/>
                                                  <Edge fillStyle0="2" fillStyle1="4" strokeStyle="0" edges="! 475 503| 307 574"/>
                                                  <Edge fillStyle0="1" fillStyle1="2" strokeStyle="0" edges="! 315 607| 306 612| 299 619| 300 613| 291 656| 265 652| 233 681"/>
                                                  <Edge fillStyle0="1" fillStyle1="0" strokeStyle="1" edges="! 233 681| 206 820"/>
                                                  <Edge fillStyle0="1" fillStyle1="3" strokeStyle="0" edges="! 206 820| 228 800[ 246 783 256 758| 272 715| 286 686| 269 770"/>
                                                  <Edge fillStyle0="1" fillStyle1="4" strokeStyle="0" edges="! 269 770| 266 788| 328 703| 349 664"/>
                                                  <Edge fillStyle0="1" fillStyle1="3" strokeStyle="0" edges="! 349 664| 382 594| 384 591| 368 595"/>
                                                  <Edge fillStyle0="1" fillStyle1="4" strokeStyle="0" edges="! 368 595| 367 595| 365 596"/>
                                                  <Edge fillStyle0="1" fillStyle1="3" strokeStyle="0" edges="! 365 596| 315 607"/>
                                                  <Edge fillStyle0="4" fillStyle1="3" strokeStyle="0" edges="! 375 570| 365 596"/>
                                                  <Edge fillStyle0="4" fillStyle1="3" strokeStyle="0" edges="! 368 595| 374 578| 435 558| 447 554| 455 544"/>
                                                  <Edge fillStyle0="0" fillStyle1="2" strokeStyle="0" edges="! 233 681| 233 678"/>
                                                  <Edge fillStyle0="0" fillStyle1="2" strokeStyle="1" edges="! 233 678| 248 599"/>
                                                  <Edge fillStyle0="5" fillStyle1="3" strokeStyle="0" edges="! 363 673| 351 689"/>
                                                  <Edge fillStyle0="5" fillStyle1="4" strokeStyle="0" edges="! 351 689| 346 695| 268 807"/>
                                                  <Edge fillStyle0="5" fillStyle1="2" strokeStyle="0" edges="! 268 807| 270 815| 259 821| 260 819"/>
                                                  <Edge fillStyle0="5" fillStyle1="4" strokeStyle="0" edges="! 260 819| 200 904| 200 905"/>
                                                  <Edge fillStyle0="5" fillStyle1="3" strokeStyle="0" edges="! 200 905| 199 907"/>
                                                  <Edge fillStyle0="5" fillStyle1="2" strokeStyle="0" edges="! 199 907| 198 907"/>
                                                  <Edge fillStyle0="5" fillStyle1="1" strokeStyle="0" edges="! 198 907| 196 910"/>
                                                  <Edge fillStyle0="5" fillStyle1="2" strokeStyle="0" edges="! 196 910| 197 919"/>
                                                  <Edge fillStyle0="0" fillStyle1="2" strokeStyle="0" edges="! 197 919| 195 921"/>
                                                  <Edge fillStyle0="0" fillStyle1="1" strokeStyle="1" edges="! 195 921| 185 926| 187 917"/>
                                                  <Edge fillStyle0="0" fillStyle1="3" strokeStyle="0" edges="! 187 917| 188 913"/>
                                                  <Edge fillStyle0="0" fillStyle1="4" strokeStyle="0" edges="! 188 913| 189 910"/>
                                                  <Edge fillStyle0="0" fillStyle1="4" strokeStyle="1" edges="! 189 910| 189 908| 200 849"/>
                                                  <Edge fillStyle0="0" fillStyle1="3" strokeStyle="1" edges="! 200 849| 206 820"/>
                                                  <Edge fillStyle0="4" fillStyle1="3" strokeStyle="0" edges="! 351 689| 351 688| 352 671| 349 664"/>
                                                  <Edge fillStyle0="3" fillStyle1="2" strokeStyle="0" edges="! 199 906| 199 907"/>
                                                  <Edge fillStyle0="4" fillStyle1="3" strokeStyle="0" edges="! 188 913| 199 906| 200 905"/>
                                                  <Edge fillStyle0="3" fillStyle1="2" strokeStyle="0" edges="! 198 907| 199 906"/>
                                                  <Edge fillStyle0="3" fillStyle1="1" strokeStyle="0" edges="! 187 917| 197 908| 198 907"/>
                                                  <Edge fillStyle0="2" fillStyle1="1" strokeStyle="0" edges="! 196 910| 193 915| 193 917| 195 921"/>
                                                  <Edge fillStyle0="3" fillStyle1="1" strokeStyle="0" edges="! 351 834| 367 814| 425 739| 446 718"/>
                                                  <Edge fillStyle0="0" fillStyle1="1" strokeStyle="1" edges="! 388 814| 351 834"/>
                                                  <Edge fillStyle0="0" fillStyle1="3" strokeStyle="1" edges="! 351 834| 291 867"/>
                                                  <Edge fillStyle0="0" fillStyle1="1" strokeStyle="1" edges="! 291 867| 284 871"/>
                                                  <Edge fillStyle0="4" fillStyle1="2" strokeStyle="0" edges="! 260 819| 268 807"/>
                                                  <Edge fillStyle0="4" fillStyle1="3" strokeStyle="0" edges="! 269 770| 218 829| 200 849"/>
                                                  <Edge fillStyle0="3" fillStyle1="1" strokeStyle="0" edges="! 289 864| 291 867"/>
                                                  <Edge fillStyle0="3" fillStyle1="1" strokeStyle="0" edges="! 670 604| 683 611| 732 639"/>
                                                  <Edge fillStyle0="3" fillStyle1="0" strokeStyle="0" edges="! 732 639| 731 632"/>
                                                  <Edge fillStyle0="3" fillStyle1="0" strokeStyle="1" edges="! 731 632| 729 622| 722 588"/>
                                                  <Edge fillStyle0="3" fillStyle1="2" strokeStyle="0" edges="! 722 588| 664 566| 662 568| 670 604"/>
                                                  <Edge fillStyle0="1" fillStyle1="2" strokeStyle="0" edges="! 670 604| 694 718[ 718 760 756 791| 762 796"/>
                                                  <Edge fillStyle0="1" fillStyle1="0" strokeStyle="1" edges="! 762 796| 732 639"/>
                                                  <Edge fillStyle0="2" fillStyle1="5" strokeStyle="0" edges="! 610 545| 621 550| 568 557[ 646 646 678 754| 686 781| 684 779"/>
                                                  <Edge fillStyle0="2" fillStyle1="3" strokeStyle="0" edges="! 684 779| 786 926"/>
                                                  <Edge fillStyle0="2" fillStyle1="0" strokeStyle="1" edges="! 786 926| 762 796"/>
                                                  <Edge fillStyle0="1" fillStyle1="2" strokeStyle="0" edges="! 610 545| 664 566| 737 498"/>
                                                  <Edge fillStyle0="1" fillStyle1="2" strokeStyle="0" edges="! 620 578| 591 578| 598 586| 630 637| 693 731| 694 731| 683 689| 669 645| 638 605| 620 578"/>
                                                  <Edge fillStyle0="2" fillStyle1="5" strokeStyle="0" edges="! 545 581| 543 578| 531 561"/>
                                                  <Edge fillStyle0="5" fillStyle1="3" strokeStyle="0" edges="! 545 581| 606 668"/>
                                                  <Edge fillStyle0="5" fillStyle1="1" strokeStyle="0" edges="! 606 668| 654 737"/>
                                                  <Edge fillStyle0="5" fillStyle1="2" strokeStyle="0" edges="! 654 737| 659 743"/>
                                                  <Edge fillStyle0="5" fillStyle1="1" strokeStyle="0" edges="! 659 743| 684 779"/>
                                                  <Edge fillStyle0="3" fillStyle1="1" strokeStyle="0" edges="! 684 779| 631 757[ 516 710 516 685[ 516 672 533 638| 545 642[ 570 642 606 668"/>
                                                  <Edge fillStyle0="3" fillStyle1="4" strokeStyle="0" edges="! 543 578| 526 589[ 510 603 504 628| 492 668"/>
                                                  <Edge fillStyle0="4" fillStyle1="5" strokeStyle="0" edges="! 531 561| 518 542| 512 533| 501 518| 494 508"/>
                                                  <Edge fillStyle0="4" fillStyle1="1" strokeStyle="0" edges="! 494 508| 490 507"/>
                                                  <Edge fillStyle0="4" fillStyle1="3" strokeStyle="0" edges="! 490 507| 488 510"/>
                                                  <Edge fillStyle0="4" fillStyle1="1" strokeStyle="0" edges="! 488 510| 488 522"/>
                                                  <Edge fillStyle0="1" fillStyle1="3" strokeStyle="0" edges="! 488 510| 488 508| 490 507"/>
                                                  <Edge fillStyle0="1" fillStyle1="3" strokeStyle="0" edges="! 491 500| 487 498| 487 499"/>
                                                  <Edge fillStyle0="1" fillStyle1="5" strokeStyle="0" edges="! 494 508| 489 500| 494 501"/>
                                                  <Edge fillStyle0="1" fillStyle1="4" strokeStyle="0" edges="! 494 501| 491 500"/>
                                                  <Edge fillStyle0="3" fillStyle1="4" strokeStyle="0" edges="! 491 500| 495 496"/>
                                                  <Edge fillStyle0="3" fillStyle1="1" strokeStyle="0" edges="! 495 496| 487 498"/>
                                                  <Edge fillStyle0="3" fillStyle1="4" strokeStyle="0" edges="! 487 498| 475 503"/>
                                                  <Edge fillStyle0="1" fillStyle1="2" strokeStyle="0" edges="! 467 549[ 436 584 408 637| 365 725[ 413 707 439 684[ 466 660 457 639| 469 549| 467 549"/>
                                                  <Edge fillStyle0="4" fillStyle1="1" strokeStyle="0" edges="! 491 646| 492 667"/>
                                                  <Edge fillStyle0="4" fillStyle1="3" strokeStyle="0" edges="! 561 800[ 547 781 543 765| 533 723| 493 700"/>
                                                  <Edge fillStyle0="4" fillStyle1="5" strokeStyle="0" edges="! 494 501| 559 526"/>
                                                  <Edge fillStyle0="0" fillStyle1="4" strokeStyle="1" edges="! 542 790| 494 764"/>
                                                  <Edge fillStyle0="4" fillStyle1="4" strokeStyle="1" edges="! 542 790| 561 800"/>
                                                  <Edge fillStyle0="3" fillStyle1="0" strokeStyle="1" edges="! 561 800| 643 846"/>
                                                  <Edge fillStyle0="3" fillStyle1="3" strokeStyle="1" edges="! 643 846| 652 851"/>
                                                  <Edge fillStyle0="3" fillStyle1="1" strokeStyle="0" edges="! 652 851| 645 844| 580 772| 585 752| 677 803| 681 811| 707 863| 713 885"/>
                                                  <Edge fillStyle0="3" fillStyle1="0" strokeStyle="1" edges="! 713 885| 786 926"/>
                                                  <Edge fillStyle0="0" fillStyle1="4" strokeStyle="0" edges="! 561 800| 561 801| 542 790"/>
                                                  <Edge fillStyle0="1" fillStyle1="2" strokeStyle="0" edges="! 659 743| 659 744| 654 737"/>
                                                  <Edge fillStyle0="0" fillStyle1="3" strokeStyle="0" edges="! 652 851| 653 852| 643 846"/>
                                                  <Edge fillStyle0="1" fillStyle1="0" strokeStyle="1" edges="! 652 851| 713 885"/>
                                                  <Edge fillStyle0="1" fillStyle1="5" strokeStyle="0" edges="! 574 531| 610 545"/>
                                                  <Edge fillStyle0="0" fillStyle1="1" strokeStyle="1" edges="! 188 529| 96 443"/>
                                                  <Edge fillStyle0="4" fillStyle1="1" strokeStyle="0" edges="! 564 474| 495 496"/>
                                                  <Edge fillStyle0="0" fillStyle1="2" strokeStyle="1" edges="! 864 454| 722 588"/>
                                             </edges>
                                        </DOMShape>
                                   </elements>
                              </DOMFrame>
                         </frames>
                    </DOMLayer>
               </layers>
          </DOMTimeline>
     </timeline>
</DOMSymbolItem>
