<DOMSymbolItem xmlns="http://ns.adobe.com/xfl/2008/" xmlns:xsi="http://www.w3.org/2001/XMLSchema-instance" name="Symbol 5331" lastModified="1648300950">
     <timeline>
          <DOMTimeline name="Symbol 5331">
               <layers>
                    <DOMLayer name="Layer 1" color="#94e732" current="true" isSelected="true">
                         <frames>
                              <DOMFrame index="0" keyMode="9728">
                                   <elements>
                                        <DOMShape isFloating="true">
                                             <fills>
                                                  <FillStyle index="1">
                                                       <SolidColor color="#605b8a"/>
                                                  </FillStyle>
                                                  <FillStyle index="2">
                                                       <SolidColor color="#ffffff"/>
                                                  </FillStyle>
                                                  <FillStyle index="3">
                                                       <SolidColor color="#adaeda"/>
                                                  </FillStyle>
                                                  <FillStyle index="4">
                                                       <SolidColor color="#e8e8f4"/>
                                                  </FillStyle>
                                                  <FillStyle index="5">
                                                       <SolidColor color="#d6d6ed"/>
                                                  </FillStyle>
                                                  <FillStyle index="6">
                                                       <SolidColor color="#000000"/>
                                                  </FillStyle>
                                             </fills>
                                             <strokes/>
                                             <edges>
                                                  <Edge fillStyle0="0" fillStyle1="1" strokeStyle="0" edges="! 297 990[ 176 969 103 901[ 0 805 0 717[ 0 691 19 661| 37 633[ 37 625 20 611| 0 588| 0 544[ 0 487 35 395[ 66 311 100 261[ 160 171 212 118| 274 44[ 322 -1 400 0[ 650 5 778 203[ 870 347 870 515[ 870 612 864 644[ 848 727 790 743| 806 772| 810 788[ 810 843 700 923[ 661 951 611 969"/>
                                                  <Edge fillStyle0="0" fillStyle1="5" strokeStyle="0" edges="! 611 969| 586 977| 426 999| 421 999| 415 999| 410 999| 403 999| 398 999| 360 998"/>
                                                  <Edge fillStyle0="0" fillStyle1="4" strokeStyle="0" edges="! 360 998| 297 990"/>
                                                  <Edge fillStyle0="1" fillStyle1="4" strokeStyle="0" edges="! 297 990| 253 978| 236 972| 209 960| 192 952| 189 951"/>
                                                  <Edge fillStyle0="1" fillStyle1="2" strokeStyle="0" edges="! 189 951| 120 903"/>
                                                  <Edge fillStyle0="1" fillStyle1="4" strokeStyle="0" edges="! 120 903| 114 898"/>
                                                  <Edge fillStyle0="1" fillStyle1="2" strokeStyle="0" edges="! 114 898| 104 888[ 20 804 20 718[ 20 694 39 665"/>
                                                  <Edge fillStyle0="1" fillStyle1="3" strokeStyle="0" edges="! 39 665| 40 663| 51 647| 60 629| 60 628| 40 599| 36 593"/>
                                                  <Edge fillStyle0="1" fillStyle1="4" strokeStyle="0" edges="! 36 593| 29 580"/>
                                                  <Edge fillStyle0="1" fillStyle1="2" strokeStyle="0" edges="! 29 580[ 20 560 20 541[ 20 505 62 395[ 99 299 116 271| 217 137[ 281 61 328 36"/>
                                                  <Edge fillStyle0="1" fillStyle1="4" strokeStyle="0" edges="! 328 36[ 342 28 355 25| 370 23| 425 28| 420 20| 465 29"/>
                                                  <Edge fillStyle0="1" fillStyle1="5" strokeStyle="0" edges="! 465 29[ 525 43 584 70| 610 82[ 740 147 775 241| 835 395[ 850 440 850 518| 845 631[ 844 657 816 694"/>
                                                  <Edge fillStyle0="1" fillStyle1="3" strokeStyle="0" edges="! 816 694| 807 705| 783 731| 771 745"/>
                                                  <Edge fillStyle0="1" fillStyle1="2" strokeStyle="0" edges="! 771 745| 770 747"/>
                                                  <Edge fillStyle0="1" fillStyle1="3" strokeStyle="0" edges="! 770 747[ 770 756 780 771| 783 775"/>
                                                  <Edge fillStyle0="1" fillStyle1="5" strokeStyle="0" edges="! 783 775| 790 792[ 790 835 699 911[ 657 947 611 969"/>
                                                  <Edge fillStyle0="2" fillStyle1="4" strokeStyle="0" edges="! 29 580[ 40 550 90 541| 102 545[ 93 544 72 552[ 55 560 51 563[ 42 577 42 586| 45 594"/>
                                                  <Edge fillStyle0="2" fillStyle1="3" strokeStyle="0" edges="! 45 594[ 58 602 84 625"/>
                                                  <Edge fillStyle0="2" fillStyle1="4" strokeStyle="0" edges="! 84 625| 77 618| 86 623[ 126 643 166 651| 225 675[ 277 696 298 696| 400 683[ 482 687 491 682| 495 671[ 510 666 521 657| 535 646| 609 626[ 675 605 685 593[ 718 550 725 514| 726 441| 725 398[ 722 372 710 358| 668 316[ 641 291 641 280| 656 253| 605 217| 565 195[ 556 184 557 161[ 558 138 547 128[ 510 95 466 77[ 420 58 328 36"/>
                                                  <Edge fillStyle0="3" fillStyle1="4" strokeStyle="0" edges="! 260 733| 228 723[ 214 719 145 680| 125 661| 84 625"/>
                                                  <Edge fillStyle0="3" fillStyle1="4" strokeStyle="0" edges="! 45 594| 37 590| 36 593"/>
                                                  <Edge fillStyle0="3" fillStyle1="2" strokeStyle="0" edges="! 39 665| 32 678| 117 703| 125 707[ 253 778 505 778| 518 778"/>
                                                  <Edge fillStyle0="3" fillStyle1="4" strokeStyle="0" edges="! 518 778| 540 778| 543 778| 560 778| 570 777"/>
                                                  <Edge fillStyle0="3" fillStyle1="5" strokeStyle="0" edges="! 570 777| 576 777| 636 773| 652 770| 700 761| 758 770| 783 775"/>
                                                  <Edge fillStyle0="5" fillStyle1="4" strokeStyle="0" edges="! 465 29[ 533 57 575 93[ 613 125 676 203[ 697 225 730 311[ 766 402 766 446| 763 469| 761 495| 767 521| 771 545[ 771 567 749 604[ 727 640 706 653[ 688 664 636 673| 637 681[ 637 699 620 713[ 597 733 548 733[ 534 733 524 725| 517 718| 516 718| 515 718"/>
                                                  <Edge fillStyle0="5" fillStyle1="4" strokeStyle="0" edges="! 516 718| 511 713[ 518 699 534 689| 525 691[ 499 707 444 719| 311 733| 245 728| 260 733"/>
                                                  <Edge fillStyle0="5" fillStyle1="3" strokeStyle="0" edges="! 260 733| 391 752| 416 754| 423 754| 446 755| 505 756[ 634 756 745 722| 816 694"/>
                                                  <Edge fillStyle0="2" fillStyle1="4" strokeStyle="0" edges="! 140 850| 140 825| 166 827| 186 840| 155 855| 140 850"/>
                                                  <Edge fillStyle0="2" fillStyle1="4" strokeStyle="0" edges="! 114 898| 117 892[ 130 872 151 870| 131 885[ 120 896 120 903"/>
                                                  <Edge fillStyle0="2" fillStyle1="4" strokeStyle="0" edges="! 167 883[ 178 853 218 858[ 257 862 257 886[ 257 893 235 898| 208 903[ 193 903 179 893| 167 883"/>
                                                  <Edge fillStyle0="2" fillStyle1="4" strokeStyle="0" edges="! 422 254[ 422 234 466 198[ 510 162 510 186| 516 204| 522 221| 516 258[ 504 286 465 286[ 437 286 427 271| 422 254"/>
                                                  <Edge fillStyle0="6" fillStyle1="2" strokeStyle="0" edges="! 422 403| 427 426| 426 446| 410 461| 400 462[ 397 462 397 454[ 397 444 404 427[ 413 406 422 403"/>
                                                  <Edge fillStyle0="6" fillStyle1="2" strokeStyle="0" edges="! 672 403[ 681 421 682 438[ 679 445 666 445| 655 441[ 652 440 652 428[ 652 413 672 403"/>
                                                  <Edge fillStyle0="2" fillStyle1="6" strokeStyle="0" edges="! 642 488| 641 454[ 641 365 678 382[ 715 399 715 464| 705 497[ 692 518 675 518[ 647 518 642 488"/>
                                                  <Edge fillStyle0="2" fillStyle1="4" strokeStyle="0" edges="! 540 599[ 540 648 463 648| 411 646| 401 631| 422 611| 447 596[ 513 578 528 579[ 540 580 540 599"/>
                                                  <Edge fillStyle0="2" fillStyle1="6" strokeStyle="0" edges="! 387 458[ 387 387 429 377[ 470 367 470 453[ 470 518 425 518[ 401 518 391 488| 387 458"/>
                                                  <Edge fillStyle0="2" fillStyle1="4" strokeStyle="0" edges="! 305 633| 291 615| 277 603[ 314 582 333 590[ 347 595 347 608[ 347 617 332 625[ 318 633 305 633"/>
                                                  <Edge fillStyle0="4" fillStyle1="2" strokeStyle="0" edges="! 518 778| 539 804[ 571 837 571 853[ 571 887 532 913[ 467 956 315 956| 189 951"/>
                                                  <Edge fillStyle0="4" fillStyle1="2" strokeStyle="0" edges="! 567 899[ 567 894 593 873[ 621 850 636 858| 637 876| 633 899[ 622 912 580 918[ 567 907 567 899"/>
                                                  <Edge fillStyle0="5" fillStyle1="4" strokeStyle="0" edges="! 570 777| 615 798[ 670 822 670 833[ 670 884 603 928[ 517 984 362 985| 360 997| 360 998"/>
                                                  <Edge fillStyle0="5" fillStyle1="4" strokeStyle="0" edges="! 779 643| 782 654[ 782 676 750 686| 730 676| 727 669[ 727 655 735 648[ 748 638 786 633| 775 640| 779 643"/>
                                                  <Edge fillStyle0="3" fillStyle1="2" strokeStyle="0" edges="! 770 747| 767 746| 765 745| 771 745"/>
                                             </edges>
                                        </DOMShape>
                                   </elements>
                              </DOMFrame>
                         </frames>
                    </DOMLayer>
               </layers>
          </DOMTimeline>
     </timeline>
</DOMSymbolItem>
