<DOMSymbolItem xmlns="http://ns.adobe.com/xfl/2008/" xmlns:xsi="http://www.w3.org/2001/XMLSchema-instance" name="Symbol 7697" lastModified="1648300950" symbolType="graphic">
     <timeline>
          <DOMTimeline name="Symbol 7697" currentFrame="0">
               <layers>
                    <DOMLayer name="Layer 1">
                         <frames>
                              <DOMFrame index="0" motionTweenScale="false" keyMode="8192">
                                   <elements>
                                        <DOMShape isFloating="true">
                                             <fills>
                                                  <FillStyle index="1">
                                                       <SolidColor color="#ffcc00" alpha="0.32941177"/>
                                                  </FillStyle>
                                                  <FillStyle index="2">
                                                       <SolidColor color="#ffcc00" alpha="0.6627451"/>
                                                  </FillStyle>
                                                  <FillStyle index="3">
                                                       <SolidColor color="#ffffff" alpha="1.0"/>
                                                  </FillStyle>
                                                  <FillStyle index="4">
                                                       <SolidColor color="#ffcc00" alpha="1.0"/>
                                                  </FillStyle>
                                             </fills>
                                             <strokes/>
                                             <edges>
                                                  <Edge fillStyle0="1" fillStyle1="0" strokeStyle="0" edges="! 190 9| 126 45| 86 40| 43 26| 40 25| 39 25| 38 26| 29 33| 28 34| 28 36| 39 137| 1 219| 1 222| 3 238| 4 240| 6 240| 91 255| 142 317"/>
                                                  <Edge fillStyle0="1" fillStyle1="4" strokeStyle="0" edges="! 142 317| 143 316| 147 307| 150 307| 152 307"/>
                                                  <Edge fillStyle0="1" fillStyle1="2" strokeStyle="0" edges="! 152 307| 150 305"/>
                                                  <Edge fillStyle0="1" fillStyle1="4" strokeStyle="0" edges="! 150 305| 149 305| 148 305| 149 303"/>
                                                  <Edge fillStyle0="1" fillStyle1="2" strokeStyle="0" edges="! 149 303| 102 246| 94 241| 13 227| 14 227| 14 226| 18 217"/>
                                                  <Edge fillStyle0="1" fillStyle1="4" strokeStyle="0" edges="! 18 217| 8 212| 11 212| 20 214"/>
                                                  <Edge fillStyle0="1" fillStyle1="2" strokeStyle="0" edges="! 20 214| 52 143| 53 136| 43 41| 81 54| 82 54| 126 60| 133 58| 193 24"/>
                                                  <Edge fillStyle0="1" fillStyle1="4" strokeStyle="0" edges="! 193 24| 192 23| 191 17| 190 9"/>
                                                  <Edge fillStyle0="0" fillStyle1="4" strokeStyle="0" edges="! 190 9| 190 5| 193 8"/>
                                                  <Edge fillStyle0="0" fillStyle1="1" strokeStyle="0" edges="! 193 8| 205 1| 206 0| 208 1| 219 3| 219 9| 220 10| 229 105| 296 182| 295 181| 291 195| 291 197| 290 197| 210 237| 177 311| 176 311| 175 313"/>
                                                  <Edge fillStyle0="0" fillStyle1="4" strokeStyle="0" edges="! 175 313| 176 314| 177 315[ 180 319 175 315"/>
                                                  <Edge fillStyle0="0" fillStyle1="1" strokeStyle="0" edges="! 175 315| 169 328| 168 329| 167 330| 156 333| 155 333| 154 332| 142 318"/>
                                                  <Edge fillStyle0="0" fillStyle1="4" strokeStyle="0" edges="! 142 318| 142 317"/>
                                                  <Edge fillStyle0="2" fillStyle1="1" strokeStyle="0" edges="! 42 38| 42 39| 43 39| 42 34| 42 38"/>
                                                  <Edge fillStyle0="1" fillStyle1="2" strokeStyle="0" edges="! 42 38| 41 39"/>
                                                  <Edge fillStyle0="2" fillStyle1="3" strokeStyle="0" edges="! 34 216| 65 149| 68 134| 60 62| 77 67| 78 68| 127 74| 140 71| 194 40"/>
                                                  <Edge fillStyle0="2" fillStyle1="4" strokeStyle="0" edges="! 194 40| 192 25| 202 29| 207 30"/>
                                                  <Edge fillStyle0="2" fillStyle1="1" strokeStyle="0" edges="! 207 30| 207 29"/>
                                                  <Edge fillStyle0="2" fillStyle1="4" strokeStyle="0" edges="! 207 29| 206 29| 193 24"/>
                                                  <Edge fillStyle0="4" fillStyle1="1" strokeStyle="0" edges="! 191 17| 191 13| 195 23| 194 23| 193 21| 191 17"/>
                                                  <Edge fillStyle0="2" fillStyle1="1" strokeStyle="0" edges="! 206 17| 207 16| 206 15| 206 17"/>
                                                  <Edge fillStyle0="1" fillStyle1="2" strokeStyle="0" edges="! 206 17| 207 24"/>
                                                  <Edge fillStyle0="1" fillStyle1="4" strokeStyle="0" edges="! 207 24| 210 28| 207 29"/>
                                                  <Edge fillStyle0="1" fillStyle1="2" strokeStyle="0" edges="! 205 12| 206 14| 206 13.5| 204 4| 212 13| 207 15| 206 13.5| 205 12"/>
                                                  <Edge fillStyle0="2" fillStyle1="4" strokeStyle="0" edges="! 202 19| 207 24"/>
                                                  <Edge fillStyle0="2" fillStyle1="1" strokeStyle="0" edges="! 206 17| 202 19"/>
                                                  <Edge fillStyle0="4" fillStyle1="1" strokeStyle="0" edges="! 202 19| 193 8"/>
                                                  <Edge fillStyle0="2" fillStyle1="1" strokeStyle="0" edges="! 208 16| 216 17| 212 13| 208 16| 207 15| 207 16| 208 16"/>
                                                  <Edge fillStyle0="4" fillStyle1="1" strokeStyle="0" edges="! 208 33| 211 31| 207 30"/>
                                                  <Edge fillStyle0="4" fillStyle1="2" strokeStyle="0" edges="! 194 40| 208 33"/>
                                                  <Edge fillStyle0="1" fillStyle1="2" strokeStyle="0" edges="! 208 33| 215 106| 218 115| 271 175"/>
                                                  <Edge fillStyle0="1" fillStyle1="4" strokeStyle="0" edges="! 271 175[ 273 173 276 172| 272 176"/>
                                                  <Edge fillStyle0="1" fillStyle1="2" strokeStyle="0" edges="! 272 176| 281 186| 268 192| 203 224[ 198 226 196 231| 165 301"/>
                                                  <Edge fillStyle0="1" fillStyle1="4" strokeStyle="0" edges="! 165 301| 175 313"/>
                                                  <Edge fillStyle0="2" fillStyle1="3" strokeStyle="0" edges="! 194 40| 200 108| 207 124| 257 181"/>
                                                  <Edge fillStyle0="2" fillStyle1="4" strokeStyle="0" edges="! 257 181| 271 175"/>
                                                  <Edge fillStyle0="1" fillStyle1="2" strokeStyle="0" edges="! 281 187| 282 186| 282 187| 281 187| 279 189| 277 192| 279 188| 279 189| 280 187| 281 187"/>
                                                  <Edge fillStyle0="4" fillStyle1="2" strokeStyle="0" edges="! 268 181| 266 184| 268 192| 268 181| 268 180"/>
                                                  <Edge fillStyle0="2" fillStyle1="4" strokeStyle="0" edges="! 268 180| 269 178"/>
                                                  <Edge fillStyle0="2" fillStyle1="4" strokeStyle="0" edges="! 268 180| 266 181| 266 182| 264 188| 257 181"/>
                                                  <Edge fillStyle0="2" fillStyle1="3" strokeStyle="0" edges="! 257 181| 197 211[ 187 215 183 225| 155 288"/>
                                                  <Edge fillStyle0="2" fillStyle1="4" strokeStyle="0" edges="! 155 288| 165 301"/>
                                                  <Edge fillStyle0="2" fillStyle1="4" strokeStyle="0" edges="! 272 176| 268 180"/>
                                                  <Edge fillStyle0="4" fillStyle1="2" strokeStyle="0" edges="! 155 288| 149 303"/>
                                                  <Edge fillStyle0="4" fillStyle1="2" strokeStyle="0" edges="! 152 307| 153 307"/>
                                                  <Edge fillStyle0="1" fillStyle1="4" strokeStyle="0" edges="! 147 310| 150 307"/>
                                                  <Edge fillStyle0="4" fillStyle1="1" strokeStyle="0" edges="! 147 310| 152 307"/>
                                                  <Edge fillStyle0="2" fillStyle1="1" strokeStyle="0" edges="! 152 307| 159 315| 163 306"/>
                                                  <Edge fillStyle0="2" fillStyle1="4" strokeStyle="0" edges="! 163 306| 153 307| 157 303| 150 305"/>
                                                  <Edge fillStyle0="1" fillStyle1="4" strokeStyle="0" edges="! 147 310| 142 318"/>
                                                  <Edge fillStyle0="4" fillStyle1="1" strokeStyle="0" edges="! 163 306| 164 306| 164 305"/>
                                                  <Edge fillStyle0="4" fillStyle1="1" strokeStyle="0" edges="! 164 306| 175 315"/>
                                                  <Edge fillStyle0="2" fillStyle1="1" strokeStyle="0" edges="! 165 323| 161 318| 159 319| 165 323"/>
                                                  <Edge fillStyle0="2" fillStyle1="1" strokeStyle="0" edges="! 159 319| 158 319| 158 320| 159 319"/>
                                                  <Edge fillStyle0="2" fillStyle1="1" strokeStyle="0" edges="! 158 320| 157 320| 158 319| 157 319| 156 323| 158 320"/>
                                                  <Edge fillStyle0="4" fillStyle1="2" strokeStyle="0" edges="! 18 217| 25 221| 27 225| 29 218| 30 225| 34 216| 20 214"/>
                                                  <Edge fillStyle0="2" fillStyle1="3" strokeStyle="0" edges="! 155 288| 114 237[ 107 228 96 227| 34 216"/>
                                             </edges>
                                        </DOMShape>
                                   </elements>
                              </DOMFrame>
                         </frames>
                    </DOMLayer>
               </layers>
          </DOMTimeline>
     </timeline>
</DOMSymbolItem>
