<DOMSymbolItem xmlns="http://ns.adobe.com/xfl/2008/" xmlns:xsi="http://www.w3.org/2001/XMLSchema-instance" name="Symbol 10575" lastModified="1648300950" linkageClassName="EpicBattleFantasy4_fla.stunt_1497" linkageExportForAS="true">
     <timeline>
          <DOMTimeline name="Symbol 10575">
               <layers>
                    <DOMLayer name="Script Layer" color="#0eeaec">
                         <frames>
                              <DOMFrame index="0" keyMode="9728">
                                   <Actionscript>
                                        <script>Options.translate(this);
</script>
                                   </Actionscript>
                                   <elements/>
                              </DOMFrame>
                         </frames>
                    </DOMLayer>
                    <DOMLayer name="Layer 2" color="#4bcff2" current="true" isSelected="true">
                         <frames>
                              <DOMFrame index="0" keyMode="9728">
                                   <elements>
                                        <DOMStaticText left="-99.2" antiAliasSharpness="0" antiAliasThickness="0" width="1323" height="871" autoExpand="true" isSelectable="false">
                                             <matrix>
                                                  <Matrix tx="6.9" ty="-10.5" a="0.475433349609375" d="0.3513336181640625" b="0.0" c="-0.0970306396484375"/>
                                             </matrix>
                                             <textRuns>
                                                  <DOMTextRun>
                                                       <characters>STUN</characters>
                                                       <textAttrs>
                                                            <DOMTextAttrs aliasText="false" rotation="true" size="49.0" bitmapSize="980" letterSpacing="0.05" indent="0" leftMargin="40" lineSpacing="0" rightMargin="0" fillColor="#ffffff" face="Impact"/>
                                                       </textAttrs>
                                                  </DOMTextRun>
                                             </textRuns>
                                             <filters>
                                                  <BevelFilter blurX="9" blurY="9" quality="3" angle="85.99962217930423" distance="5.0" highlightColor="#66ffff" shadowColor="#ffcc00" strength="1.5"/>
                                                  <GlowFilter blurX="3" blurY="3" color="#666666" quality="1" strength="10"/>
                                             </filters>
                                        </DOMStaticText>
                                   </elements>
                              </DOMFrame>
                              <DOMFrame index="1" keyMode="9728">
                                   <elements>
                                        <DOMStaticText left="-99.2" antiAliasSharpness="0" antiAliasThickness="0" width="2287" height="1006" autoExpand="true" isSelectable="false">
                                             <matrix>
                                                  <Matrix tx="3.4" ty="-10.5" a="0.475433349609375" d="0.3513336181640625" b="0.0" c="-0.0970306396484375"/>
                                             </matrix>
                                             <textRuns>
                                                  <DOMTextRun>
                                                       <characters>PARÁLISIS</characters>
                                                       <textAttrs>
                                                            <DOMTextAttrs aliasText="false" rotation="true" size="49.0" bitmapSize="980" letterSpacing="0" indent="0" leftMargin="10" lineSpacing="0" rightMargin="0" fillColor="#ffffff" face="Impact"/>
                                                       </textAttrs>
                                                  </DOMTextRun>
                                             </textRuns>
                                             <filters>
                                                  <BevelFilter blurX="9" blurY="9" quality="3" angle="85.99962217930423" distance="5.0" highlightColor="#66ffff" shadowColor="#ffcc00" strength="1.5"/>
                                                  <GlowFilter blurX="3" blurY="3" color="#666666" quality="1" strength="10"/>
                                             </filters>
                                        </DOMStaticText>
                                   </elements>
                              </DOMFrame>
                              <DOMFrame index="2" keyMode="9728">
                                   <elements>
                                        <DOMStaticText left="-99.2" antiAliasSharpness="0" antiAliasThickness="0" width="2282" height="871" autoExpand="true" isSelectable="false">
                                             <matrix>
                                                  <Matrix tx="6.9" ty="-10.5" a="0.475433349609375" d="0.3513336181640625" b="0.0" c="-0.0970306396484375"/>
                                             </matrix>
                                             <textRuns>
                                                  <DOMTextRun>
                                                       <characters>PARALISIA</characters>
                                                       <textAttrs>
                                                            <DOMTextAttrs aliasText="false" rotation="true" size="49.0" bitmapSize="980" letterSpacing="0" indent="0" leftMargin="15" lineSpacing="0" rightMargin="0" fillColor="#ffffff" face="Impact"/>
                                                       </textAttrs>
                                                  </DOMTextRun>
                                             </textRuns>
                                             <filters>
                                                  <BevelFilter blurX="9" blurY="9" quality="3" angle="85.99962217930423" distance="5.0" highlightColor="#66ffff" shadowColor="#ffcc00" strength="1.5"/>
                                                  <GlowFilter blurX="3" blurY="3" color="#666666" quality="1" strength="10"/>
                                             </filters>
                                        </DOMStaticText>
                                   </elements>
                              </DOMFrame>
                              <DOMFrame index="3" keyMode="9728">
                                   <elements>
                                        <DOMStaticText left="-99.2" antiAliasSharpness="0" antiAliasThickness="0" width="2595" height="1001" autoExpand="true" isSelectable="false">
                                             <matrix>
                                                  <Matrix tx="6.9" ty="-10.5" a="0.475433349609375" d="0.3513336181640625" b="0.0" c="-0.0970306396484375"/>
                                             </matrix>
                                             <textRuns>
                                                  <DOMTextRun>
                                                       <characters>BETÄUBUNG</characters>
                                                       <textAttrs>
                                                            <DOMTextAttrs aliasText="false" rotation="true" size="49.0" bitmapSize="980" letterSpacing="0" indent="0" leftMargin="6" lineSpacing="0" rightMargin="0" fillColor="#ffffff" face="Impact"/>
                                                       </textAttrs>
                                                  </DOMTextRun>
                                             </textRuns>
                                             <filters>
                                                  <BevelFilter blurX="9" blurY="9" quality="3" angle="85.99962217930423" distance="5.0" highlightColor="#66ffff" shadowColor="#ffcc00" strength="1.5"/>
                                                  <GlowFilter blurX="3" blurY="3" color="#666666" quality="1" strength="10"/>
                                             </filters>
                                        </DOMStaticText>
                                   </elements>
                              </DOMFrame>
                              <DOMFrame index="4" keyMode="9728">
                                   <elements>
                                        <DOMStaticText left="-99.2" antiAliasSharpness="0" antiAliasThickness="0" width="2328" height="871" autoExpand="true" isSelectable="false">
                                             <matrix>
                                                  <Matrix tx="6.9" ty="-10.5" a="0.475433349609375" d="0.3513336181640625" b="0.0" c="-0.0970306396484375"/>
                                             </matrix>
                                             <textRuns>
                                                  <DOMTextRun>
                                                       <characters>PARALYSIE</characters>
                                                       <textAttrs>
                                                            <DOMTextAttrs aliasText="false" rotation="true" size="49.0" bitmapSize="980" letterSpacing="0" indent="0" leftMargin="11" lineSpacing="0" rightMargin="0" fillColor="#ffffff" face="Impact"/>
                                                       </textAttrs>
                                                  </DOMTextRun>
                                             </textRuns>
                                             <filters>
                                                  <BevelFilter blurX="9" blurY="9" quality="3" angle="85.99962217930423" distance="5.0" highlightColor="#66ffff" shadowColor="#ffcc00" strength="1.5"/>
                                                  <GlowFilter blurX="3" blurY="3" color="#666666" quality="1" strength="10"/>
                                             </filters>
                                        </DOMStaticText>
                                   </elements>
                              </DOMFrame>
                         </frames>
                    </DOMLayer>
               </layers>
          </DOMTimeline>
     </timeline>
</DOMSymbolItem>
