<DOMSymbolItem xmlns="http://ns.adobe.com/xfl/2008/" xmlns:xsi="http://www.w3.org/2001/XMLSchema-instance" name="Symbol 923" lastModified="1648300950" symbolType="graphic">
     <timeline>
          <DOMTimeline name="Symbol 923" currentFrame="0">
               <layers>
                    <DOMLayer name="Layer 1">
                         <frames>
                              <DOMFrame index="0" motionTweenScale="false" keyMode="8192">
                                   <elements>
                                        <DOMShape isFloating="true">
                                             <fills>
                                                  <FillStyle index="1">
                                                       <BitmapFill bitmapPath="bitmap200.png">
                                                            <matrix>
                                                                 <Matrix tx="20.45" ty="288.25" a="1.64111328125" d="-1.528228759765625" b="-9.696746826171875" c="-9.029647827148438"/>
                                                            </matrix>
                                                       </BitmapFill>
                                                  </FillStyle>
                                                  <FillStyle index="2">
                                                       <BitmapFill bitmapPath="bitmap216.png">
                                                            <matrix>
                                                                 <Matrix tx="116.9" ty="449.5" a="0.4611663818359375" d="-0.074798583984375" b="-15.868087768554688" c="-9.168609619140625"/>
                                                            </matrix>
                                                       </BitmapFill>
                                                  </FillStyle>
                                             </fills>
                                             <strokes/>
                                             <edges>
                                                  <Edge fillStyle0="2" fillStyle1="0" strokeStyle="0" edges="! -2038 2458| -2060 2457[ -2113 2495 -2064 2593| -1933 2594| -1929 2458| -2037 2458"/>
                                                  <Edge fillStyle0="2" fillStyle1="1" strokeStyle="0" edges="! -2037 2458| -2042 2479| -2038 2458"/>
                                                  <Edge fillStyle0="0" fillStyle1="1" strokeStyle="0" edges="! -2038 2458| -2037 2458"/>
                                             </edges>
                                        </DOMShape>
                                   </elements>
                              </DOMFrame>
                         </frames>
                    </DOMLayer>
               </layers>
          </DOMTimeline>
     </timeline>
</DOMSymbolItem>
